modelmapper/__init__.py
modelmapper/base.py
modelmapper/cleaner.py
modelmapper/etl.py
modelmapper/excel.py
modelmapper/exceptions.py
modelmapper/gpg.py
modelmapper/initialize.py
modelmapper/loader.py
modelmapper/management.py
modelmapper/mapper.py
modelmapper/misc.py
modelmapper/normalization.py
modelmapper/s3.py
modelmapper/sftp.py
modelmapper/signature.py
modelmapper/slack.py
modelmapper/stats.py
modelmapper/types.py
modelmapper/ui.py
modelmapper/templates/setup_template.toml
tests/fixtures/__init__.py
tests/fixtures/analysis_fixtures.py
tests/fixtures/cleaning_err_registry_fixtures.py
tests/fixtures/etl.py
tests/fixtures/excel_fixtures.py
tests/fixtures/training_fixture1_cleaned_for_import.py
tests/fixtures/training_fixture1_mapping.py
tests/fixtures/training_fixture1_with_2_sheets_cleaned_for_import.py
modelmapper-1.5.1.dist-info/AUTHORS
modelmapper-1.5.1.dist-info/LICENSE
modelmapper-1.5.1.dist-info/METADATA
modelmapper-1.5.1.dist-info/WHEEL
modelmapper-1.5.1.dist-info/entry_points.txt
modelmapper-1.5.1.dist-info/top_level.txt
modelmapper-1.5.1.dist-info/RECORD
