Metadata-Version: 2.1
Name: modelmapper
Version: 1.5.1
Summary: Auto generate SQLalchemy models, cleaning and field normalization from your csv files.
Home-page: https://github.com/wearefair/modelmapper
Author: Sep Dehpour
Author-email: sepd@fair.com
License: UNKNOWN
Download-URL: https://github.com/wearefair/modelmapper/tarball/master
Platform: UNKNOWN
Classifier: Intended Audience :: Developers
Classifier: Operating System :: OS Independent
Classifier: Topic :: Software Development
Classifier: Programming Language :: Python :: 3.6
Classifier: Programming Language :: Python :: 3.7
Classifier: Development Status :: 5 - Production/Stable
Requires-Dist: pytoml (>=0.1.16)
Requires-Dist: clevercsv (>=0.6.3)
Requires-Dist: click (>=6.7)
Requires-Dist: cchardet (>=2.1.6)
Requires-Dist: tabulate (>=0.8.2)
Requires-Dist: xlrd (>=1.1.0)
Requires-Dist: paramiko (>=2.7.1)
